lydoc/__init__.py
lydoc/_version.py
lydoc/collector.py
lydoc/console.py
lydoc/lilyparser.py
lydoc/metrics.py
lydoc/renderer.py
lydoc/templates/markdown.j2
lydoc/templates/restructuredtext.j2
lydoc-0.1.1.dist-info/DESCRIPTION.rst
lydoc-0.1.1.dist-info/METADATA
lydoc-0.1.1.dist-info/RECORD
lydoc-0.1.1.dist-info/WHEEL
lydoc-0.1.1.dist-info/entry_points.txt
lydoc-0.1.1.dist-info/metadata.json
lydoc-0.1.1.dist-info/top_level.txt
