Metadata-Version: 2.0
Name: lydoc
Version: 0.1.1
Summary: An API documentation generator for Lilypond files
Home-page: https://github.com/Cecca/lydoc
Author: Matteo Ceccarello
Author-email: matteo.ceccarello@gmail.com
License: GPLv3
Platform: UNKNOWN
Classifier: License :: OSI Approved :: GNU General Public License v3 (GPLv3)
Classifier: Programming Language :: Python :: 3.3
Classifier: Programming Language :: Python :: 3.4
Classifier: Programming Language :: Python :: 2.7
Classifier: Programming Language :: Python :: 2
Classifier: Programming Language :: Python :: 3
Classifier: Programming Language :: Python :: 3.5
Classifier: Development Status :: 3 - Alpha
Requires-Dist: grako
Requires-Dist: jinja2
Provides-Extra: dev
Requires-Dist: pyinstaller; extra == 'dev'
Provides-Extra: test
Requires-Dist: coverage; extra == 'test'
Requires-Dist: nose; extra == 'test'
